onedevcommonclickup/__init__.py
onedevcommonclickup/criaAlerta.py
onedevcommonclickup/filtroAlertas.py
onedevcommonclickup/updateTasks.py
onedevcommonclickup-1.0.5.dist-info/METADATA
onedevcommonclickup-1.0.5.dist-info/WHEEL
onedevcommonclickup-1.0.5.dist-info/RECORD
