Metadata-Version: 2.4
Name: onedevcommonclickup
Version: 1.0.5
Summary: Biblioteca para integração com ClickUp
Project-URL: Homepage, https://github.com/onedev/onedev-common-ms-graph
Project-URL: Repository, https://github.com/onedev/onedev-common-ms-graph.git
Project-URL: Documentation, https://github.com/onedev/onedev-common-ms-graph#readme
Author-email: Giovani <giovani.moreira@ufly.com.br>
License: MIT
Classifier: License :: OSI Approved :: MIT License
Classifier: Operating System :: OS Independent
Classifier: Programming Language :: Python :: 3
Requires-Python: >=3.8
Requires-Dist: msal>=1.25.0
Requires-Dist: requests>=2.31.0
